EvoloPy/__init__.py
EvoloPy/api.py
EvoloPy/benchmarks.py
EvoloPy/cli.py
EvoloPy/optimizer.py
EvoloPy/parallel_utils.py
EvoloPy/plot_boxplot.py
EvoloPy/plot_convergence.py
EvoloPy/solution.py
EvoloPy/optimizers/BAT.py
EvoloPy/optimizers/CS.py
EvoloPy/optimizers/DE.py
EvoloPy/optimizers/FFA.py
EvoloPy/optimizers/GA.py
EvoloPy/optimizers/GWO.py
EvoloPy/optimizers/HHO.py
EvoloPy/optimizers/JAYA.py
EvoloPy/optimizers/MFO.py
EvoloPy/optimizers/MVO.py
EvoloPy/optimizers/PSO.py
EvoloPy/optimizers/SCA.py
EvoloPy/optimizers/SSA.py
EvoloPy/optimizers/WOA.py
EvoloPy/optimizers/__init__.py
evolopy-4.0.6.dist-info/licenses/LICENSE.txt
evolopy-4.0.6.dist-info/METADATA
evolopy-4.0.6.dist-info/WHEEL
evolopy-4.0.6.dist-info/entry_points.txt
evolopy-4.0.6.dist-info/top_level.txt
evolopy-4.0.6.dist-info/RECORD
