Metadata-Version: 2.4
Name: EvoloPy
Version: 4.0.6
Summary: An open source nature-inspired optimization toolbox with parallel processing capabilities
Home-page: https://github.com/7ossam81/EvoloPy
Author: EvoloPy Team
Author-email: Hossam Faris <hossam.faris@ju.edu.jo>
Maintainer: Jaber Jaber
Maintainer-email: Raneem Qaddoura <raneem.qaddoura@gmail.com>, Jaber Jaber <jaber2jabet@gmail.com>
License: MIT
Project-URL: Homepage, https://github.com/7ossam81/EvoloPy
Project-URL: Bug Tracker, https://github.com/7ossam81/EvoloPy/issues
Project-URL: Source Code, https://github.com/7ossam81/EvoloPy
Project-URL: Contributors, https://github.com/7ossam81/EvoloPy/graphs/contributors
Keywords: optimization,meta-heuristic,evolutionary,swarm intelligence,parallel,gpu-accelerated
Classifier: Development Status :: 4 - Beta
Classifier: Intended Audience :: Science/Research
Classifier: Intended Audience :: Developers
Classifier: License :: OSI Approved :: MIT License
Classifier: Programming Language :: Python :: 3
Classifier: Programming Language :: Python :: 3.6
Classifier: Programming Language :: Python :: 3.7
Classifier: Programming Language :: Python :: 3.8
Classifier: Programming Language :: Python :: 3.9
Classifier: Topic :: Scientific/Engineering :: Artificial Intelligence
Requires-Python: >=3.6
License-File: LICENSE.txt
Requires-Dist: numpy>=1.19.0
Requires-Dist: pandas>=1.0.0
Requires-Dist: scipy>=1.5.0
Requires-Dist: matplotlib>=3.3.0
Requires-Dist: scikit-learn>=0.23.0
Requires-Dist: psutil>=5.8.0
Provides-Extra: gpu
Requires-Dist: torch>=1.7.0; extra == "gpu"
Dynamic: author
Dynamic: home-page
Dynamic: license-file
Dynamic: maintainer
Dynamic: requires-python
